BasicVector/__init__.py
BasicVector/colors.py
BasicVector/errors.py
BasicVector/locals.py
BasicVector/vec2.py
BasicVector/vec3.py
BasicVector/vec4.py
BasicVector-0.0.9.dist-info/LICENSE
BasicVector-0.0.9.dist-info/METADATA
BasicVector-0.0.9.dist-info/WHEEL
BasicVector-0.0.9.dist-info/top_level.txt
BasicVector-0.0.9.dist-info/RECORD
