Metadata-Version: 2.1
Name: BasicVector
Version: 0.0.9
Summary: Basic vector lib with basic functions
Home-page: https://framagit.org/PLOTFINDER/python-basic-vector
Author: PLOTFINDER
Author-email: anas.yakoubov.s@gmail.com
License: UNKNOWN
Project-URL: Bug Tracker, https://framagit.org/PLOTFINDER/python-basic-vector/-/issues
Platform: UNKNOWN
Classifier: Programming Language :: Python :: 3
Classifier: License :: OSI Approved :: MIT License
Classifier: Operating System :: OS Independent
Requires-Python: >=3.6
License-File: LICENSE
